benchpred/__init__.py
benchpred/aipw.py
benchpred/anchor_points.py
benchpred/base.py
benchpred/deepcore.py
benchpred/double_optimize.py
benchpred/lasso.py
benchpred/pca.py
benchpred/random.py
benchpred/tiny_bench.py
benchpred/py_irt/__init__.py
benchpred/py_irt/cli.py
benchpred/py_irt/config.py
benchpred/py_irt/dataset.py
benchpred/py_irt/initializers.py
benchpred/py_irt/io.py
benchpred/py_irt/scoring.py
benchpred/py_irt/training.py
benchpred/py_irt/models/__init__.py
benchpred/py_irt/models/abstract_model.py
benchpred/py_irt/models/multidim_2pl.py
benchpred-1.0.0.dist-info/licenses/LICENSE.txt
benchpred-1.0.0.dist-info/METADATA
benchpred-1.0.0.dist-info/WHEEL
benchpred-1.0.0.dist-info/top_level.txt
benchpred-1.0.0.dist-info/RECORD
