Metadata-Version: 2.4
Name: benchpred
Version: 1.0.0
Summary: Tools for benchmark prediction with fewer data.
Author: Guanhua Zhang
License: MIT
Classifier: Development Status :: 3 - Alpha
Classifier: License :: OSI Approved :: MIT License
Classifier: Intended Audience :: Science/Research
Classifier: Topic :: Scientific/Engineering :: Artificial Intelligence
Classifier: Natural Language :: English
Classifier: Programming Language :: Python :: 3
Classifier: Programming Language :: Python :: 3.7
Classifier: Programming Language :: Python :: 3.8
Classifier: Programming Language :: Python :: 3.9
Classifier: Programming Language :: Python :: 3.10
Classifier: Programming Language :: Python :: 3.11
Classifier: Programming Language :: Python :: 3.12
Requires-Python: >=3.7
License-File: LICENSE.txt
Requires-Dist: py-irt==0.4.10
Requires-Dist: torch
Requires-Dist: kmedoids
Requires-Dist: datasets
Requires-Dist: pyro-ppl
Requires-Dist: pyyaml
Requires-Dist: matplotlib
Requires-Dist: tqdm
Requires-Dist: pandas
Requires-Dist: numpy==1.26.4
Requires-Dist: joblib
Requires-Dist: gitpython
Requires-Dist: ipython
Requires-Dist: wandb
Requires-Dist: scikit-learn
Requires-Dist: ordered_set
Requires-Dist: rich
Dynamic: license-file
